jupyterlab_mathjax2/__init__.py
jupyterlab_mathjax2/_version.py
jupyterlab_mathjax2-4.0.0.data/data/share/jupyter/labextensions/@jupyterlab/mathjax2-extension/package.json
jupyterlab_mathjax2-4.0.0.data/data/share/jupyter/labextensions/@jupyterlab/mathjax2-extension/static/643.dc773165bf78df3b8401.js
jupyterlab_mathjax2-4.0.0.data/data/share/jupyter/labextensions/@jupyterlab/mathjax2-extension/static/650.f04341c2ef0ad86bed54.js
jupyterlab_mathjax2-4.0.0.data/data/share/jupyter/labextensions/@jupyterlab/mathjax2-extension/static/remoteEntry.85005ed0aa7590f1eaf8.js
jupyterlab_mathjax2-4.0.0.data/data/share/jupyter/labextensions/@jupyterlab/mathjax2-extension/static/style.js
jupyterlab_mathjax2-4.0.0.data/data/share/jupyter/labextensions/@jupyterlab/mathjax2-extension/static/third-party-licenses.json
jupyterlab_mathjax2-4.0.0.data/data/share/jupyter/labextensions/@jupyterlab/mathjax2-extension/install.json
jupyterlab_mathjax2-4.0.0.dist-info/METADATA
jupyterlab_mathjax2-4.0.0.dist-info/WHEEL
jupyterlab_mathjax2-4.0.0.dist-info/licenses/LICENSE
jupyterlab_mathjax2-4.0.0.dist-info/RECORD
