Metadata-Version: 2.1
Name: jupyterlab_mathjax2
Version: 4.0.0
Summary: A MathJax Typesetting provider for JupyterLab 4 and above
Project-URL: Homepage, https://github.com/jupyterlab/jupyter-renderers.git
Project-URL: Bug Tracker, https://github.com/jupyterlab/jupyter-renderers.git/issues
Project-URL: Repository, https://github.com/jupyterlab/jupyter-renderers.git.git
Author-email: Project Jupyter <jupyter@googlegroups.com>
License: BSD 3-Clause License
License-File: LICENSE
Classifier: Framework :: Jupyter
Classifier: Framework :: Jupyter :: JupyterLab
Classifier: Framework :: Jupyter :: JupyterLab :: 4
Classifier: Framework :: Jupyter :: JupyterLab :: Extensions
Classifier: Framework :: Jupyter :: JupyterLab :: Extensions :: Prebuilt
Classifier: License :: OSI Approved :: BSD License
Classifier: Programming Language :: Python
Classifier: Programming Language :: Python :: 3
Classifier: Programming Language :: Python :: 3.8
Classifier: Programming Language :: Python :: 3.9
Classifier: Programming Language :: Python :: 3.10
Classifier: Programming Language :: Python :: 3.11
Requires-Python: >=3.8
